bookgen/__init__.py
bookgen/bookgen.py
bookgen-1.0.0.dist-info/LICENSE
bookgen-1.0.0.dist-info/METADATA
bookgen-1.0.0.dist-info/WHEEL
bookgen-1.0.0.dist-info/top_level.txt
bookgen-1.0.0.dist-info/RECORD
