Metadata-Version: 2.1
Name: bookgen
Version: 1.0.0
Summary: Generates books based on other books using nltk
Home-page: https://github.com/Gelbpunkt/bookgen
Author: Jens Reidel
Author-email: jens.reidel@gmail.com
License: MIT
Platform: UNKNOWN
Classifier: Programming Language :: Python :: 3
Classifier: License :: OSI Approved :: MIT License
Classifier: Operating System :: OS Independent
Requires-Dist: nltk
